README.rst
setup.py
eventview/__init__.py
eventview/main.py
eventview/parser.py
eventview/reader.py
jw.eventview.egg-info/PKG-INFO
jw.eventview.egg-info/SOURCES.txt
jw.eventview.egg-info/dependency_links.txt
jw.eventview.egg-info/entry_points.txt
jw.eventview.egg-info/requires.txt
jw.eventview.egg-info/top_level.txt