Metadata-Version: 1.1
Name: jw.eventview
Version: 0.2.1
Summary: Real-time event viewer
Home-page: https://pypi.python.org/pypi/jw.eventview
Author: Johnny Wezel
Author-email: dev-jay@wezel.name
License: GPL
Keywords: real-time event viewer
Platform: POSIX
Classifier: Development Status :: 3 - Alpha
Classifier: Environment :: X11 Applications
Classifier: Intended Audience :: Developers
Classifier: License :: OSI Approved :: GNU General Public License v3 or later (GPLv3+)
Classifier: Natural Language :: English
Classifier: Operating System :: POSIX
Classifier: Operating System :: Unix
Classifier: Programming Language :: Python :: 2
Classifier: Programming Language :: Python :: 2.7
Classifier: Programming Language :: Python :: 3
Classifier: Programming Language :: Python :: 3.4
